word_gen_card-0.1.3.dist-info/METADATA
word_gen_card-0.1.3.dist-info/WHEEL
word_gen_card-0.1.3.dist-info/entry_points.txt
word_gen_card-0.1.3.dist-info/licenses/LICENSE
word_gen_card/__init__.py
word_gen_card/base.py
word_gen_card/cli.py
word_gen_card/eudic.py
word_gen_card-0.1.3.dist-info/RECORD
