Metadata-Version: 2.1
Name: word_gen_card
Version: 0.1.3
Summary: a generate anki card  tool from dictionary export csv file
Author-Email: Jay Lau <cappyclear@gmail.com>
License: MIT
Project-URL: Repository, https://github.com/lau-jay/word-gen-card
Requires-Python: >=3.10
Requires-Dist: genanki==0.13.1
Requires-Dist: edge-tts==6.1.11
